tulliolo/bip39/__init__.py
tulliolo/bip39/mnemonic.py
tulliolo/bip39/wordlist.py
tulliolo/bip39/cli/__init__.py
tulliolo/bip39/cli/__main__.py
tulliolo/bip39/cli/command.py
tulliolo/bip39/cli/generate.py
tulliolo/bip39/cli/steganography.py
tulliolo/bip39/cli/transform.py
tulliolo/bip39/cli/validate.py
tulliolo/bip39/utils/__init__.py
tulliolo/bip39/utils/common.py
tulliolo/bip39/utils/encryption.py
tulliolo/bip39/utils/steganography.py
tulliolo/bip39/utils/transformation.py
tulliolo.bip39-0.2.dist-info/LICENSE
tulliolo.bip39-0.2.dist-info/METADATA
tulliolo.bip39-0.2.dist-info/WHEEL
tulliolo.bip39-0.2.dist-info/entry_points.txt
tulliolo.bip39-0.2.dist-info/top_level.txt
tulliolo.bip39-0.2.dist-info/RECORD
