Metadata-Version: 2.1
Name: tulliolo.bip39
Version: 0.2
Summary: A bip39 implementation, with a collection of tools
Author-email: "Tullio Loffredo (@tulliolo)" <tulliolo@yahoo.com>
License: Copyright (c) 2023 Tullio Loffredo (@tulliolo)
Project-URL: Homepage, https://github.com/tulliolo/bip39
Project-URL: Bug Tracker, https://github.com/tulliolo/bip39/issues
Project-URL: Documentation, https://github.com/tulliolo/bip39/wiki
Keywords: bitcoin,bip39,entropy,mnemonic,seed,cryptography,steganography
Classifier: Development Status :: 4 - Beta
Classifier: License :: OSI Approved :: MIT License
Classifier: Programming Language :: Python
Classifier: Programming Language :: Python :: 3
Classifier: Programming Language :: Python :: 3.9
Classifier: Programming Language :: Python :: 3.10
Classifier: Programming Language :: Python :: 3.11
Classifier: Operating System :: OS Independent
Classifier: Topic :: Security
Classifier: Topic :: Utilities
Requires-Python: >=3.9
License-File: LICENSE
Requires-Dist: pillow (~=9.5.0)
Requires-Dist: cryptography (~=40.0.2)
Requires-Dist: pyreadline3 (~=3.4.1)
